payu/__init__.py
payu/client.py
payu/enumerators.py
payu/exceptions.py
payu/payments.py
payu/queries.py
payu/recurring.py
payu/tokenization.py
payu/utils.py
payu_python_v2-0.1.8.dist-info/licenses/LICENSE
payu_python_v2-0.1.8.dist-info/METADATA
payu_python_v2-0.1.8.dist-info/WHEEL
payu_python_v2-0.1.8.dist-info/top_level.txt
payu_python_v2-0.1.8.dist-info/RECORD
