Metadata-Version: 2.4
Name: payu-python-v2
Version: 0.1.8
Summary: API wrapper for Payu written in Python
Home-page: https://github.com/teatrix/payu-python
Author: Miguel Ferrer
Author-email: ingferrermiguel@gmail.com
License: MIT
License-File: LICENSE
Requires-Dist: requests
Dynamic: author
Dynamic: author-email
Dynamic: description
Dynamic: description-content-type
Dynamic: home-page
Dynamic: license
Dynamic: license-file
Dynamic: requires-dist
Dynamic: summary
